geomodelr/__init__.py
geomodelr/__main__.py
geomodelr/cpp.so
geomodelr/faults.py
geomodelr/model.py
geomodelr/shared.py
geomodelr/test.py
geomodelr/utils.py
geomodelr-0.1.3.dist-info/DESCRIPTION.rst
geomodelr-0.1.3.dist-info/LICENSE.txt
geomodelr-0.1.3.dist-info/METADATA
geomodelr-0.1.3.dist-info/RECORD
geomodelr-0.1.3.dist-info/WHEEL
geomodelr-0.1.3.dist-info/entry_points.txt
geomodelr-0.1.3.dist-info/metadata.json
geomodelr-0.1.3.dist-info/top_level.txt
