Metadata-Version: 2.0
Name: geomodelr
Version: 0.1.3
Summary: Geomodelr is the open source query tool for geomodelr.com models.
Home-page: http://github.com/rserrano/geomodelr
Author: Ricardo Serrano
Author-email: rserrano@geomodelr.com
License: AGPL
Keywords: geology,geological modelling,cross sections,geomodelr
Platform: UNKNOWN
Requires-Dist: numpy
Requires-Dist: scipy
Requires-Dist: shapely
